{"id":1,"address":{"street":"Main Street","zipcode":"12345"},"borough":"Brooklyn","name":"Brooklyn High School","students":[{"student_id":"12345","name":"John Doe","grade":"A"},{"student_id":"67890","name":"Jane Smith","grade":"B"}],"teachers":[{"teacher_id":"T123","name":"Mr. Johnson","subject":"Math"},{"teacher_id":"T456","name":"Ms. Davis","subject":"Science"}],"facilities":{"classrooms":20,"gymnasium":true,"library":true}}
{"id":2,"address":{"street":"Oak Street","zipcode":"56789"},"borough":"Manhattan","name":"Manhattan High School","students":[{"student_id":"11111","name":"Alice Johnson","grade":"A"},{"student_id":"22222","name":"Bob Smith","grade":"B"}],"teachers":[{"teacher_id":"T789","name":"Mrs. Brown","subject":"English"},{"teacher_id":"T101","name":"Mr. White","subject":"History"}],"facilities":{"classrooms":25,"gymnasium":true,"library":true}}
{"id":3,"address":{"street":"Maple Street","zipcode":"98765"},"borough":"Queens","name":"Queens High School","students":[{"student_id":"33333","name":"Eva Wilson","grade":"B"},{"student_id":"44444","name":"Chris Anderson","grade":"A"}],"teachers":[{"teacher_id":"T222","name":"Mrs. Garcia","subject":"Physics"},{"teacher_id":"T333","name":"Mr. Smith","subject":"Chemistry"}],"facilities":{"classrooms":15,"gymnasium":true,"library":false}}
{"id":4,"address":{"street":"Pine Street","zipcode":"54321"},"borough":"Bronx","name":"Bronx High School","students":[{"student_id":"55555","name":"Alex Turner","grade":"A"},{"student_id":"66666","name":"Linda Martinez","grade":"B"}],"teachers":[{"teacher_id":"T444","name":"Mr. Brown","subject":"Computer Science"},{"teacher_id":"T555","name":"Ms. Wilson","subject":"Art"}],"facilities":{"classrooms":18,"gymnasium":false,"library":true}}
{"id":5,"address":{"street":"Cedar Street","zipcode":"13579"},"borough":"Staten Island","name":"Staten Island High School","students":[{"student_id":"77777","name":"Sophia Rodriguez","grade":"B"},{"student_id":"88888","name":"David Lee","grade":"A"}],"teachers":[{"teacher_id":"T666","name":"Mrs. Turner","subject":"Spanish"},{"teacher_id":"T777","name":"Mr. Martinez","subject":"Physical Education"}],"facilities":{"classrooms":22,"gymnasium":true,"library":true}}
{"id":6,"address":{"street":"Elm Street","zipcode":"24680"},"borough":"Brooklyn","name":"Brooklyn Junior High","students":[{"student_id":"99999","name":"Olivia Hernandez","grade":"A"},{"student_id":"10101","name":"Michael Taylor","grade":"B"}],"teachers":[{"teacher_id":"T888","name":"Ms. Garcia","subject":"Social Studies"},{"teacher_id":"T999","name":"Mr. Turner","subject":"Music"}],"facilities":{"classrooms":17,"gymnasium":true,"library":true}}
{"id":7,"address":{"street":"Sycamore Street","zipcode":"11223"},"borough":"Queens","name":"Queens Junior High","students":[{"student_id":"12121","name":"Sophie Clark","grade":"B"},{"student_id":"13131","name":"Jack Davis","grade":"A"}],"teachers":[{"teacher_id":"T1010","name":"Mrs. Rodriguez","subject":"Biology"},{"teacher_id":"T1111","name":"Mr. Hernandez","subject":"Geography"}],"facilities":{"classrooms":19,"gymnasium":false,"library":true}}
{"id":8,"address":{"street":"Redwood Street","zipcode":"33445"},"borough":"Manhattan","name":"Manhattan Junior High","students":[{"student_id":"14141","name":"Emma Brown","grade":"A"},{"student_id":"15151","name":"Christopher White","grade":"B"}],"teachers":[{"teacher_id":"T1212","name":"Mr. Taylor","subject":"Chemistry"},{"teacher_id":"T1313","name":"Ms. Turner","subject":"Math"}],"facilities":{"classrooms":23,"gymnasium":true,"library":true}}
{"id":9,"address":{"street":"Birch Street","zipcode":"55667"},"borough":"Bronx","name":"Bronx Junior High","students":[{"student_id":"16161","name":"Daniel Garcia","grade":"B"},{"student_id":"17171","name":"Mia Turner","grade":"A"}],"teachers":[{"teacher_id":"T1414","name":"Mrs. Hernandez","subject":"History"},{"teacher_id":"T1515","name":"Mr. Clark","subject":"Physics"}],"facilities":{"classrooms":21,"gymnasium":true,"library":false}}
{"id":10,"address":{"street":"Ash Street","zipcode":"77889"},"borough":"Staten Island","name":"Staten Island Junior High","students":[{"student_id":"18181","name":"Isaac Martinez","grade":"A"},{"student_id":"19191","name":"Ava Rodriguez","grade":"B"}],"teachers":[{"teacher_id":"T1616","name":"Mr. Davis","subject":"Computer Science"},{"teacher_id":"T1717","name":"Ms. Clark","subject":"English"}],"facilities":{"classrooms":20,"gymnasium":true,"library":true}}
{"id":11,"address":{"street":"Cherry Street","zipcode":"99011"},"borough":"Brooklyn","name":"Brooklyn Elementary School","students":[{"student_id":"20202","name":"Grace Smith","grade":"A"},{"student_id":"21212","name":"William Brown","grade":"B"}],"teachers":[{"teacher_id":"T1818","name":"Mrs. Turner","subject":"Art"},{"teacher_id":"T1919","name":"Mr. Davis","subject":"Math"}],"facilities":{"classrooms":14,"gymnasium":false,"library":true}}
{"id":12,"address":{"street":"Willow Street","zipcode":"22334"},"borough":"Queens","name":"Queens Elementary School","students":[{"student_id":"22222","name":"Ryan Martinez","grade":"B"},{"student_id":"23232","name":"Ella Hernandez","grade":"A"}],"teachers":[{"teacher_id":"T2020","name":"Ms. Taylor","subject":"Physical Education"},{"teacher_id":"T2121","name":"Mr. White","subject":"Science"}],"facilities":{"classrooms":16,"gymnasium":true,"library":true}}
{"id":13,"address":{"street":"Poplar Street","zipcode":"44556"},"borough":"Manhattan","name":"Manhattan Elementary School","students":[{"student_id":"24242","name":"Liam Turner","grade":"A"},{"student_id":"25252","name":"Chloe Davis","grade":"B"}],"teachers":[{"teacher_id":"T2222","name":"Mrs. Brown","subject":"Spanish"},{"teacher_id":"T2323","name":"Mr. Taylor","subject":"Social Studies"}],"facilities":{"classrooms":18,"gymnasium":true,"library":false}}
{"id":14,"address":{"street":"Magnolia Street","zipcode":"66778"},"borough":"Bronx","name":"Bronx Elementary School","students":[{"student_id":"26262","name":"Zoe White","grade":"B"},{"student_id":"27272","name":"James Clark","grade":"A"}],"teachers":[{"teacher_id":"T2424","name":"Mr. Turner","subject":"Music"},{"teacher_id":"T2525","name":"Ms. Garcia","subject":"Geography"}],"facilities":{"classrooms":20,"gymnasium":true,"library":true}}
{"id":15,"address":{"street":"Cypress Street","zipcode":"88990"},"borough":"Staten Island","name":"Staten Island Elementary School","students":[{"student_id":"28282","name":"Sophie Taylor","grade":"A"},{"student_id":"29292","name":"Jackson Brown","grade":"B"}],"teachers":[{"teacher_id":"T2626","name":"Mr. Davis","subject":"History"},{"teacher_id":"T2727","name":"Ms. Hernandez","subject":"Biology"}],"facilities":{"classrooms":22,"gymnasium":true,"library":true}}
  
